atom/dict.pyi
atom/typing_utils.py
atom/instance.py
atom/catom.cpython-311-darwin.so
atom/tuple.py
atom/typed.py
atom/event.py
atom/subclass.py
atom/property.pyi
atom/version.py
atom/signal.py
atom/list.py
atom/set.pyi
atom/property.py
atom/scalars.pyi
atom/delegator.py
atom/containerlist.pyi
atom/coerced.py
atom/__init__.py
atom/containerlist.py
atom/typed.pyi
atom/api.py
atom/coerced.pyi
atom/delegator.pyi
atom/catom.pyi
atom/event.pyi
atom/instance.pyi
atom/py.typed
atom/list.pyi
atom/dict.py
atom/tuple.pyi
atom/enum.py
atom/scalars.py
atom/set.py
atom/atom.py
atom/signal.pyi
atom/subclass.pyi
atom/enum.pyi
atom/datastructures/sortedmap.cpython-311-darwin.so
atom/datastructures/__init__.py
atom/datastructures/api.py
atom/datastructures/sortedmap.pyi
atom/meta/observation.py
atom/meta/annotation_utils.py
atom/meta/member_modifiers.py
atom/meta/__init__.py
atom/meta/atom_meta.py
atom-0.12.1.dist-info/RECORD
atom-0.12.1.dist-info/WHEEL
atom-0.12.1.dist-info/top_level.txt
atom-0.12.1.dist-info/METADATA
atom-0.12.1.dist-info/licenses/LICENSE
