Metadata-Version: 2.4
Name: atom
Version: 0.12.1
Summary: Memory efficient Python objects
Author-email: The Nucleic Development Team <sccolbert@gmail.com>
Maintainer-email: "Matthieu C. Dartiailh" <m.dartiailh@gmail.com>
License-Expression: BSD-3-Clause
Project-URL: homepage, https://github.com/nucleic/atom
Project-URL: documentation, https://atom.readthedocs.io/en/latest/
Project-URL: repository, https://github.com/nucleic/atom
Project-URL: changelog, https://github.com/nucleic/atom/blob/main/releasenotes.rst
Classifier: Programming Language :: Python
Classifier: Programming Language :: Python :: 3
Classifier: Programming Language :: Python :: 3.10
Classifier: Programming Language :: Python :: 3.11
Classifier: Programming Language :: Python :: 3.12
Classifier: Programming Language :: Python :: 3.13
Classifier: Programming Language :: Python :: 3.14
Classifier: Programming Language :: Python :: Implementation :: CPython
Requires-Python: >=3.10
License-File: LICENSE
Requires-Dist: typing_extensions; python_version < "3.11"
Dynamic: license-file
